latexvm/__init__.py
latexvm/expression.py
latexvm/graph_session.py
latexvm/type_defs.py
latexvm-0.1.6.dist-info/METADATA
latexvm-0.1.6.dist-info/WHEEL
latexvm-0.1.6.dist-info/RECORD
